{"hellenica":[[1,1],[2,1],[3,1],[4,1],[5,1],[6,1],[7,1]],"βιβλίον":[[1,1],[2,1],[3,1],[4,1],[5,1],[6,1],[7,1],[8,1],[9,1],[10,1],[11,1],[15,1],[16,1],[17,1],[18,1],[19,1],[20,1],[21,1],[22,1],[23,1],[24,1],[25,1],[26,1],[27,1],[28,1],[29,1]],"α":[[1,1],[8,1],[15,1],[22,1]],"β":[[2,1],[9,1],[16,1],[23,1]],"γ":[[3,1],[10,1],[17,1],[24,1]],"δ":[[4,1],[11,1],[18,1],[25,1]],"ε":[[5,1],[19,1],[26,1]],"ζ":[[6,1],[20,1],[27,1]],"η":[[7,1],[21,1],[28,1]],"memorabilia":[[8,1],[9,1],[10,1],[11,1]],"oeconomicus":[[12,2]],"symposium":[[13,2]],"apology":[[14,2]],"anabasis":[[15,1],[16,1],[17,1],[18,1],[19,1],[20,1],[21,1]],"cyropaedia":[[22,1],[23,1],[24,1],[25,1],[26,1],[27,1],[28,1],[29,1]],"θ":[[29,1]],"hiero":[[30,2]],"agesilaus":[[31,2]],"constitution":[[32,2]],"of":[[32,2],[35,2]],"the":[[32,2],[34,2],[35,2]],"lacedaemonians":[[32,2]],"ways":[[33,2]],"and":[[33,2]],"means":[[33,2]],"on":[[34,2],[35,2],[36,2]],"cavalry":[[34,2]],"commander":[[34,2]],"art":[[35,2]],"horsemanship":[[35,2]],"hunting":[[36,2]]}